synapy/__init__.py
synapy/supervised_synaptic_matrix.py
synapy-0.1.dist-info/DESCRIPTION.rst
synapy-0.1.dist-info/METADATA
synapy-0.1.dist-info/RECORD
synapy-0.1.dist-info/WHEEL
synapy-0.1.dist-info/metadata.json
synapy-0.1.dist-info/top_level.txt
