Metadata-Version: 2.0
Name: synapy
Version: 0.1
Summary: Synapy, a synaptic matrix implementation for Python
Home-page: http://github.com/lantunes/synapy
Author: Luis M. Antunes
Author-email: lantunes@gmail.com
License: MIT
Keywords: synaptic matrix,synapy,neurons,machine learning
Platform: UNKNOWN
Classifier: Development Status :: 3 - Alpha
Classifier: Intended Audience :: Developers
Classifier: Topic :: Scientific/Engineering :: Artificial Intelligence
Classifier: License :: OSI Approved :: MIT License
Classifier: Programming Language :: Python :: 2.6
Classifier: Programming Language :: Python :: 2.7
Classifier: Programming Language :: Python :: 3.2
Classifier: Programming Language :: Python :: 3.3
Classifier: Programming Language :: Python :: 3.4
Classifier: Programming Language :: Python :: 3.5
Requires-Dist: numpy (>=1.12.1)
